{"info":{"_postman_id":"083babe0-55a5-4193-8fbc-d0b7b4333658","name":"Basic","description":"Contains all the API which are taken as basic, like no auth just get and only provide like noraml information related to the application.","schema":"https://schema.getpostman.com/json/collection/v2.1.0/collection.json"},"item":[{"name":"/","id":"dda6d060-84eb-41a0-abe2-12169828af71","protocolProfileBehavior":{"disableBodyPruning":true},"request":{"method":"GET","header":[{"key":"X-Firebase-AppCheck","value":"asdfasdf","type":"text"}],"url":{"raw":"{{API_URL}}/","host":["{{API_URL}}"],"path":[""]},"description":"A normal get api to get the basic details of the Renter Python application."},"response":[]},{"name":"/terms_condition/<user_type>","id":"b6fa45ad-4bf2-4ef7-92c5-faf55d4774e0","protocolProfileBehavior":{"disableBodyPruning":true},"request":{"method":"GET","header":[{"key":"X-Firebase-AppCheck","value":"abcd","type":"text"}],"url":{"raw":"{{API_URL}}/terms_condition/owner","host":["{{API_URL}}"],"path":["terms_condition","owner"]},"description":"An API request which fetches the terms and condition for the given user_type."},"response":[]},{"name":"/information","id":"fbd3a4a8-fed3-4d9a-bc95-4f59a11854f6","protocolProfileBehavior":{"disableBodyPruning":true},"request":{"method":"GET","header":[{"key":"X-Firebase-AppCheck","value":"asdfasd","type":"text"}],"url":{"raw":"{{API_URL}}/information","host":["{{API_URL}}"],"path":["information"]},"description":"Fetches the information related to the renter application. This will help to be used in the application for the user to see some details related to the project."},"response":[]},{"name":"/email","id":"c3a87fd8-824e-49cd-a3b0-4839f6225436","protocolProfileBehavior":{"disableBodyPruning":true},"request":{"method":"GET","header":[{"key":"X-Firebase-AppCheck","value":"abcd","type":"text"}],"url":{"raw":"{{API_URL}}/email/pradyot@gmail.com","host":["{{API_URL}}"],"path":["email","pradyot@gmail.com"]}},"response":[]}]}